<page>
  <unknown>
Nr 10. 6 Lördagen den 26 februari.
</unknown>
  <unknown>
$ 3.
</unknown>
  <unknown>
Gemensamma = Sedan riksdagens båda kamrar förehaft och godkänt de uti statsutskottets
</unknown>
  <unknown>
omröstningar. memorial nr 14, punkterna 1 och 2, samt nr 16, punkterna 1 och 2, föreslagna voteringspropositioner rörande frågor, i vilka kamrarna fattat stridiga beslut, samt bestämt blivit, att vederbörliga omröstningar över de olika besluten skulle denna dag äga rum, så anställdes nu omröstningar enligt nedan intagna voteringspropositioner i följande ordning, nämligen:
</unknown>
  <unknown>
Första omröstningen: (enligt statsutskottets memorial nr 14, punkten 1).
</unknown>
  <unknown>
»Den, som i likhet med första kammaren vill, att riksdagen, med bifall till Kungl. Maj:ts förslag och med avslag å den av herr Lindhagen väckta motionen I: 170, till främjande av upplysningsverksamheten rörande Nationernas förbund för budgetåret 1927—1928 anvisar ett extra anslag av 2,500 kronor, röstar -
</unknown>
  <unknown>
a;
</unknown>
  <unknown>
Den, det ej vill, röstar Nej;
</unknown>
  <unknown>
Vinner Nej, har riksdagen i överensstämmelse med andra kammaren beslutat att i anledning av Kungl. Maj:ts förslag och med avslag å den av herr Lindhagen väckta motionen I: 170, i likhet med vad som för innevarande budgetår ägt rum, till svenska föreningen för Nationernas förbund för budgetåret 1927—1928 anvisa ett extra anslag av 1,500 kronor.»
</unknown>
  <unknown>
Sedan efter given varsel kammarens ledamöter intagit sina platser samt voteringspropositionen blivit uppläst, företogs omröstningen medelst namnupprop, och utföll densamma med 56 Ja och 128 Nej, varjämte 2 av kammarens ledamöter förklarade sig avstå från att rösta.
</unknown>
  <unknown>
Den omröstning över ovanintagna voteringsproposition, som, enligt ankommet och nu uppläst protokoll, blivit av första kammaren samtidigt anställd,
</unknown>
  <unknown>
hade: utfallit med. ss ss. mensen ae ses a sa sen BG di öre 59 Ja och 53 Nej, vadan, då därtill lades andra kammarens röster eller.. 56 Ja och 128 Nej, sammanräkningen Visade m-.........s...s..- &gt; nee sa .... 115 Ja och 181 Nej,
</unknown>
  <unknown>
och hade alltså beslut i denna fråga blivit av riksdagen fattat i överensstämmelse med nej-propositionens innehåll.
</unknown>
  <unknown>
Andra omröstningen: (enligt statsutskottets memorial nr 14, punkten 2).
</unknown>
  <unknown>
»Den, som i likhet med första kammaren vill, att riksdagen med bifall till herrar Lithanders samt Vennerströms m. fl. motioner (I: 76 och II: 86) för inköp av en till beskickningsfastigheten i Washington gränsande tomt, närmare omnämnd i ett av professor L. I. Wahlman avgivet, i Kungl. Maj:ts proproposition nr 167 till 1925 års riksdag återgivet utlåtande, för budgetåret 1927 —1928 anvisar ett extra anslag av 37,500 kronor, röstar
</unknown>
  <unknown>
Ja;
</unknown>
  <unknown>
Den, det ej vill, röstar
</unknown>
  <unknown>
Nej;
</unknown>
</page>
